optimal_cutoffs/__init__.py
optimal_cutoffs/algorithms/__init__.py
optimal_cutoffs/algorithms/binary.py
optimal_cutoffs/algorithms/expected.py
optimal_cutoffs/algorithms/multiclass.py
optimal_cutoffs/algorithms/multilabel.py
optimal_cutoffs/api.py
optimal_cutoffs/bayes/__init__.py
optimal_cutoffs/bayes_core.py
optimal_cutoffs/binary.py
optimal_cutoffs/core.py
optimal_cutoffs/cv/__init__.py
optimal_cutoffs/cv.py
optimal_cutoffs/expected.py
optimal_cutoffs/metrics/__init__.py
optimal_cutoffs/metrics_core.py
optimal_cutoffs/multiclass.py
optimal_cutoffs/multilabel.py
optimal_cutoffs/numba_utils.py
optimal_cutoffs/optimize.py
optimal_cutoffs/piecewise.py
optimal_cutoffs/py.typed
optimal_cutoffs/validation.py
optimal_classification_cutoffs-2.0.0.dist-info/WHEEL
optimal_classification_cutoffs-2.0.0.dist-info/METADATA
optimal_classification_cutoffs-2.0.0.dist-info/RECORD
