Metadata-Version: 2.4
Name: optimal-classification-cutoffs
Version: 2.0.0
Summary: Utilities for computing optimal classification cutoffs for binary and multiclass classification
Author: Gaurav Sood
Author-email: Gaurav Sood <contact@gsood.com>
License-Expression: MIT
Classifier: Development Status :: 4 - Beta
Classifier: Intended Audience :: Science/Research
Classifier: Programming Language :: Python :: 3
Classifier: Programming Language :: Python :: 3.12
Classifier: Programming Language :: Python :: 3.13
Classifier: Programming Language :: Python :: 3.14
Classifier: Topic :: Scientific/Engineering :: Mathematics
Requires-Dist: numpy>=1.20.0
Requires-Dist: scipy
Requires-Dist: scikit-learn
Requires-Python: >=3.12
